pyigd/__init__.py
pyigd/extra.py
pyigd/readwrite.py
pyigd-1.3.dist-info/LICENSE
pyigd-1.3.dist-info/METADATA
pyigd-1.3.dist-info/WHEEL
pyigd-1.3.dist-info/top_level.txt
pyigd-1.3.dist-info/RECORD
