Metadata-Version: 2.1
Name: pyigd
Version: 1.3
Summary: Parser for IGD files
Home-page: https://aprilweilab.github.io/
Author: Drew DeHaas
Author-email: 
License: UNKNOWN
Platform: UNKNOWN
Classifier: Programming Language :: Python :: 3
License-File: LICENSE
